girder_thumbnails/__init__.py
girder_thumbnails/rest.py
girder_thumbnails/utils.py
girder_thumbnails/worker.py
girder_thumbnails/web_client/dist/girder-plugin-thumbnails.umd.cjs
girder_thumbnails/web_client/dist/style.css
girder_thumbnails-5.0.0a14.dev27.dist-info/METADATA
girder_thumbnails-5.0.0a14.dev27.dist-info/WHEEL
girder_thumbnails-5.0.0a14.dev27.dist-info/entry_points.txt
girder_thumbnails-5.0.0a14.dev27.dist-info/top_level.txt
girder_thumbnails-5.0.0a14.dev27.dist-info/RECORD
