Metadata-Version: 2.4
Name: girder-thumbnails
Version: 5.0.0a14.dev27
Summary: Generate thumbnails from files.
Author: Kitware, Inc.
Author-email: kitware@kitware.com
License: Apache 2.0
Classifier: Development Status :: 5 - Production/Stable
Classifier: Environment :: Web Environment
Classifier: Operating System :: OS Independent
Classifier: Programming Language :: Python
Classifier: Programming Language :: Python :: 3
Requires-Python: >=3.10
Requires-Dist: girder>=3
Requires-Dist: girder-jobs>=3
Requires-Dist: Pillow
Requires-Dist: pydicom>=2
Requires-Dist: numpy
Dynamic: author
Dynamic: author-email
Dynamic: classifier
Dynamic: license
Dynamic: requires-dist
Dynamic: requires-python
Dynamic: summary
